setup.py
diffuspy/__init__.py
diffuspy/backwardeuler.py
diffuspy/boundary.py
diffuspy/constructor.py
diffuspy/element.py
diffuspy/material.py
diffuspy/picard.py
diffuspy.egg-info/PKG-INFO
diffuspy.egg-info/SOURCES.txt
diffuspy.egg-info/dependency_links.txt
diffuspy.egg-info/not-zip-safe
diffuspy.egg-info/requires.txt
diffuspy.egg-info/top_level.txt
test/test_steadystate.py
test/test_transient.py