Metadata-Version: 1.1
Name: diffuspy
Version: 0.2
Summary: General diffusion equation in 2d solver using FEM
Home-page: https://github.com/nasseralkmim/diffuspy
Author: Nasser Alkmim
Author-email: nasser.alkmim@gmail.com
License: MIT
Download-URL: https://github.com/nasseralkmim/diffuspy/releases/tag/0.2
Platform: UNKNOWN
